img2vec_pytorch/__init__.py
img2vec_pytorch/img_to_vec.py
tests/__init__.py
tests/test_img_to_vec.py
img2vec_pytorch_2-1.3.0.dist-info/LICENSE.txt
img2vec_pytorch_2-1.3.0.dist-info/METADATA
img2vec_pytorch_2-1.3.0.dist-info/WHEEL
img2vec_pytorch_2-1.3.0.dist-info/top_level.txt
img2vec_pytorch_2-1.3.0.dist-info/RECORD
