Metadata-Version: 2.2
Name: img2vec-pytorch-2
Version: 1.3.0
Summary: Use pre-trained models in PyTorch to extract vector embeddings for any image
Home-page: https://github.com/psilabs-dev/img2vec
Author: Christian Safka, psilabs-dev
Author-email: christiansafka@gmail.com, 113860476+psilabs-dev@users.noreply.github.com
License: MIT
Keywords: img2vec image vector classification pytorch convert
Classifier: License :: OSI Approved :: MIT License
Classifier: Programming Language :: Python :: 3.6
Requires-Python: >=3.6
License-File: LICENSE.txt
Requires-Dist: torch
Requires-Dist: torchvision
Requires-Dist: numpy
Dynamic: author
Dynamic: author-email
Dynamic: classifier
Dynamic: description
Dynamic: description-content-type
Dynamic: home-page
Dynamic: keywords
Dynamic: license
Dynamic: requires-dist
Dynamic: requires-python
Dynamic: summary
